atooms/__init__.py
atooms/dynamics/__init__.py
atooms/dynamics/base.py
atooms/dynamics/helpers.py
atooms/dynamics/kernels_hard.f90
atooms/dynamics/kernels_soft.f90
atooms/dynamics/newtonian.py
atooms/dynamics/stochastic.py
atooms_dynamics-2.0.0.dist-info/LICENSE
atooms_dynamics-2.0.0.dist-info/METADATA
atooms_dynamics-2.0.0.dist-info/WHEEL
atooms_dynamics-2.0.0.dist-info/top_level.txt
atooms_dynamics-2.0.0.dist-info/RECORD
