Metadata-Version: 2.1
Name: atooms-dynamics
Version: 2.0.0
Summary: Newtonian and stochastic dynamics backends for atooms
Home-page: https://framagit.org/atooms/dynamics
Author: Daniele Coslovich
Author-email: daniele.coslovich@umontpellier.fr
License: GPLv3
Platform: UNKNOWN
Classifier: License :: OSI Approved :: GNU General Public License v3 (GPLv3)
Classifier: Programming Language :: Python :: 3
Classifier: Programming Language :: Python :: 3.6
Classifier: Intended Audience :: Science/Research
Classifier: Topic :: Scientific/Engineering :: Physics
License-File: LICENSE
Requires-Dist: atooms (>=3.20.1)
Requires-Dist: f2py-jit (>=0.5.0)
